[
  {
    "player_id": "23",
    "player_name": "Alpine",
    "type": "Constructor",
    "race_number": 1,
    "race_name": "Australian Grand Prix",
    "race_flag": "🇦🇺",
    "race_date": "2026-03-08",
    "next_race_number": 2,
    "next_race_name": "Chinese Grand Prix",
    "price_this_race": 12.5,
    "price_prev_race": 12.5,
    "price_next_race": 13.1,
    "price_change": 0.6,
    "price_change_pct": 4.8,
    "gameday_points": 22,
    "total_points": 22,
    "season_high": 13.7,
    "season_low": 12.5,
    "pct_vs_high": -8.76,
    "pct_vs_low": 0.0,
    "fetched_at": "2026-03-22T11:36:10.219059+00:00"
  },
  {
    "player_id": "24",
    "player_name": "Aston Martin",
    "type": "Constructor",
    "race_number": 1,
    "race_name": "Australian Grand Prix",
    "race_flag": "🇦🇺",
    "race_date": "2026-03-08",
    "next_race_number": 2,
    "next_race_name": "Chinese Grand Prix",
    "price_this_race": 10.3,
    "price_prev_race": 10.3,
    "price_next_race": 9.7,
    "price_change": -0.6,
    "price_change_pct": -5.83,
    "gameday_points": -38,
    "total_points": -38,
    "season_high": 10.3,
    "season_low": 9.1,
    "pct_vs_high": 0.0,
    "pct_vs_low": 13.19,
    "fetched_at": "2026-03-22T11:36:11.086454+00:00"
  },
  {
    "player_id": "2640",
    "player_name": "Audi",
    "type": "Constructor",
    "race_number": 1,
    "race_name": "Australian Grand Prix",
    "race_flag": "🇦🇺",
    "race_date": "2026-03-08",
    "next_race_number": 2,
    "next_race_name": "Chinese Grand Prix",
    "price_this_race": 6.6,
    "price_prev_race": 6.6,
    "price_next_race": 6.0,
    "price_change": -0.6,
    "price_change_pct": -9.09,
    "gameday_points": null,
    "total_points": 0,
    "season_high": 6.6,
    "season_low": 5.4,
    "pct_vs_high": 0.0,
    "pct_vs_low": 22.22,
    "fetched_at": "2026-03-22T11:36:12.109633+00:00"
  },
  {
    "player_id": "2641",
    "player_name": "Cadillac",
    "type": "Constructor",
    "race_number": 1,
    "race_name": "Australian Grand Prix",
    "race_flag": "🇦🇺",
    "race_date": "2026-03-08",
    "next_race_number": 2,
    "next_race_name": "Chinese Grand Prix",
    "price_this_race": 6.0,
    "price_prev_race": 6.0,
    "price_next_race": 5.4,
    "price_change": -0.6,
    "price_change_pct": -10.0,
    "gameday_points": -13,
    "total_points": -13,
    "season_high": 6.0,
    "season_low": 5.2,
    "pct_vs_high": 0.0,
    "pct_vs_low": 15.38,
    "fetched_at": "2026-03-22T11:36:13.031057+00:00"
  },
  {
    "player_id": "25",
    "player_name": "Ferrari",
    "type": "Constructor",
    "race_number": 1,
    "race_name": "Australian Grand Prix",
    "race_flag": "🇦🇺",
    "race_date": "2026-03-08",
    "next_race_number": 2,
    "next_race_name": "Chinese Grand Prix",
    "price_this_race": 23.3,
    "price_prev_race": 23.3,
    "price_next_race": 23.6,
    "price_change": 0.3,
    "price_change_pct": 1.29,
    "gameday_points": 69,
    "total_points": 69,
    "season_high": 23.9,
    "season_low": 23.3,
    "pct_vs_high": -2.51,
    "pct_vs_low": 0.0,
    "fetched_at": "2026-03-22T11:36:13.952289+00:00"
  },
  {
    "player_id": "26",
    "player_name": "Haas F1 Team",
    "type": "Constructor",
    "race_number": 1,
    "race_name": "Australian Grand Prix",
    "race_flag": "🇦🇺",
    "race_date": "2026-03-08",
    "next_race_number": 2,
    "next_race_name": "Chinese Grand Prix",
    "price_this_race": 7.4,
    "price_prev_race": 7.4,
    "price_next_race": 8.0,
    "price_change": 0.6,
    "price_change_pct": 8.11,
    "gameday_points": 34,
    "total_points": 34,
    "season_high": 8.6,
    "season_low": 7.4,
    "pct_vs_high": -13.95,
    "pct_vs_low": 0.0,
    "fetched_at": "2026-03-22T11:36:14.875620+00:00"
  },
  {
    "player_id": "27",
    "player_name": "McLaren",
    "type": "Constructor",
    "race_number": 1,
    "race_name": "Australian Grand Prix",
    "race_flag": "🇦🇺",
    "race_date": "2026-03-08",
    "next_race_number": 2,
    "next_race_name": "Chinese Grand Prix",
    "price_this_race": 28.9,
    "price_prev_race": 28.9,
    "price_next_race": 28.8,
    "price_change": -0.1,
    "price_change_pct": -0.35,
    "gameday_points": 19,
    "total_points": 19,
    "season_high": 28.9,
    "season_low": 28.5,
    "pct_vs_high": 0.0,
    "pct_vs_low": 1.4,
    "fetched_at": "2026-03-22T11:36:15.797129+00:00"
  },
  {
    "player_id": "28",
    "player_name": "Mercedes",
    "type": "Constructor",
    "race_number": 1,
    "race_name": "Australian Grand Prix",
    "race_flag": "🇦🇺",
    "race_date": "2026-03-08",
    "next_race_number": 2,
    "next_race_name": "Chinese Grand Prix",
    "price_this_race": 29.3,
    "price_prev_race": 29.3,
    "price_next_race": 29.6,
    "price_change": 0.3,
    "price_change_pct": 1.02,
    "gameday_points": 96,
    "total_points": 96,
    "season_high": 29.9,
    "season_low": 29.3,
    "pct_vs_high": -2.01,
    "pct_vs_low": 0.0,
    "fetched_at": "2026-03-22T11:36:16.720225+00:00"
  },
  {
    "player_id": "2636",
    "player_name": "Racing Bulls",
    "type": "Constructor",
    "race_number": 1,
    "race_name": "Australian Grand Prix",
    "race_flag": "🇦🇺",
    "race_date": "2026-03-08",
    "next_race_number": 2,
    "next_race_name": "Chinese Grand Prix",
    "price_this_race": 6.3,
    "price_prev_race": 6.3,
    "price_next_race": 6.9,
    "price_change": 0.6,
    "price_change_pct": 9.52,
    "gameday_points": 35,
    "total_points": 35,
    "season_high": 7.5,
    "season_low": 6.3,
    "pct_vs_high": -16.0,
    "pct_vs_low": 0.0,
    "fetched_at": "2026-03-22T11:36:17.640732+00:00"
  },
  {
    "player_id": "29",
    "player_name": "Red Bull Racing",
    "type": "Constructor",
    "race_number": 1,
    "race_name": "Australian Grand Prix",
    "race_flag": "🇦🇺",
    "race_date": "2026-03-08",
    "next_race_number": 2,
    "next_race_name": "Chinese Grand Prix",
    "price_this_race": 28.2,
    "price_prev_race": 28.2,
    "price_next_race": 28.5,
    "price_change": 0.3,
    "price_change_pct": 1.06,
    "gameday_points": 42,
    "total_points": 42,
    "season_high": 28.8,
    "season_low": 28.2,
    "pct_vs_high": -2.08,
    "pct_vs_low": 0.0,
    "fetched_at": "2026-03-22T11:36:18.507655+00:00"
  },
  {
    "player_id": "210",
    "player_name": "Williams",
    "type": "Constructor",
    "race_number": 1,
    "race_name": "Australian Grand Prix",
    "race_flag": "🇦🇺",
    "race_date": "2026-03-08",
    "next_race_number": 2,
    "next_race_name": "Chinese Grand Prix",
    "price_this_race": 12.0,
    "price_prev_race": 12.0,
    "price_next_race": 12.6,
    "price_change": 0.6,
    "price_change_pct": 5.0,
    "gameday_points": 20,
    "total_points": 20,
    "season_high": 13.2,
    "season_low": 12.0,
    "pct_vs_high": -9.09,
    "pct_vs_low": 0.0,
    "fetched_at": "2026-03-22T11:36:19.485693+00:00"
  },
  {
    "player_id": "11",
    "player_name": "Alexander Albon",
    "type": "Driver",
    "race_number": 1,
    "race_name": "Australian Grand Prix",
    "race_flag": "🇦🇺",
    "race_date": "2026-03-08",
    "next_race_number": 2,
    "next_race_name": "Chinese Grand Prix",
    "price_this_race": 11.6,
    "price_prev_race": 11.6,
    "price_next_race": 11.4,
    "price_change": -0.2,
    "price_change_pct": -1.72,
    "gameday_points": 8,
    "total_points": 8,
    "season_high": 11.6,
    "season_low": 10.8,
    "pct_vs_high": 0.0,
    "pct_vs_low": 7.41,
    "fetched_at": "2026-03-22T11:35:51.012584+00:00"
  },
  {
    "player_id": "11149",
    "player_name": "Arvid Lindblad",
    "type": "Driver",
    "race_number": 1,
    "race_name": "Australian Grand Prix",
    "race_flag": "🇦🇺",
    "race_date": "2026-03-08",
    "next_race_number": 2,
    "next_race_name": "Chinese Grand Prix",
    "price_this_race": 6.2,
    "price_prev_race": 6.2,
    "price_next_race": 6.8,
    "price_change": 0.6,
    "price_change_pct": 9.68,
    "gameday_points": 15,
    "total_points": 15,
    "season_high": 7.4,
    "season_low": 6.2,
    "pct_vs_high": -16.22,
    "pct_vs_low": 0.0,
    "fetched_at": "2026-03-22T11:35:52.037391+00:00"
  },
  {
    "player_id": "125",
    "player_name": "Carlos Sainz",
    "type": "Driver",
    "race_number": 1,
    "race_name": "Australian Grand Prix",
    "race_flag": "🇦🇺",
    "race_date": "2026-03-08",
    "next_race_number": 2,
    "next_race_name": "Chinese Grand Prix",
    "price_this_race": 11.8,
    "price_prev_race": 11.8,
    "price_next_race": 11.6,
    "price_change": -0.2,
    "price_change_pct": -1.69,
    "gameday_points": 9,
    "total_points": 9,
    "season_high": 12.2,
    "season_low": 11.6,
    "pct_vs_high": -3.28,
    "pct_vs_low": 1.72,
    "fetched_at": "2026-03-22T11:35:52.650753+00:00"
  },
  {
    "player_id": "115",
    "player_name": "Charles Leclerc",
    "type": "Driver",
    "race_number": 1,
    "race_name": "Australian Grand Prix",
    "race_flag": "🇦🇺",
    "race_date": "2026-03-08",
    "next_race_number": 2,
    "next_race_name": "Chinese Grand Prix",
    "price_this_race": 22.8,
    "price_prev_race": 22.8,
    "price_next_race": 23.1,
    "price_change": 0.3,
    "price_change_pct": 1.32,
    "gameday_points": 29,
    "total_points": 29,
    "season_high": 23.4,
    "season_low": 22.8,
    "pct_vs_high": -2.56,
    "pct_vs_low": 0.0,
    "fetched_at": "2026-03-22T11:35:53.572376+00:00"
  },
  {
    "player_id": "118",
    "player_name": "Esteban Ocon",
    "type": "Driver",
    "race_number": 1,
    "race_name": "Australian Grand Prix",
    "race_flag": "🇦🇺",
    "race_date": "2026-03-08",
    "next_race_number": 2,
    "next_race_name": "Chinese Grand Prix",
    "price_this_race": 7.3,
    "price_prev_race": 7.3,
    "price_next_race": 7.9,
    "price_change": 0.6,
    "price_change_pct": 8.22,
    "gameday_points": 9,
    "total_points": 9,
    "season_high": 8.5,
    "season_low": 7.3,
    "pct_vs_high": -14.12,
    "pct_vs_low": 0.0,
    "fetched_at": "2026-03-22T11:35:54.498318+00:00"
  },
  {
    "player_id": "12",
    "player_name": "Fernando Alonso",
    "type": "Driver",
    "race_number": 1,
    "race_name": "Australian Grand Prix",
    "race_flag": "🇦🇺",
    "race_date": "2026-03-08",
    "next_race_number": 2,
    "next_race_name": "Chinese Grand Prix",
    "price_this_race": 10.0,
    "price_prev_race": 10.0,
    "price_next_race": 9.4,
    "price_change": -0.6,
    "price_change_pct": -6.0,
    "gameday_points": -14,
    "total_points": -14,
    "season_high": 10.0,
    "season_low": 8.8,
    "pct_vs_high": 0.0,
    "pct_vs_low": 13.64,
    "fetched_at": "2026-03-22T11:35:55.417783+00:00"
  },
  {
    "player_id": "11059",
    "player_name": "Franco Colapinto",
    "type": "Driver",
    "race_number": 1,
    "race_name": "Australian Grand Prix",
    "race_flag": "🇦🇺",
    "race_date": "2026-03-08",
    "next_race_number": 2,
    "next_race_name": "Chinese Grand Prix",
    "price_this_race": 6.2,
    "price_prev_race": 6.2,
    "price_next_race": 6.4,
    "price_change": 0.2,
    "price_change_pct": 3.23,
    "gameday_points": 6,
    "total_points": 6,
    "season_high": 7.0,
    "season_low": 6.2,
    "pct_vs_high": -11.43,
    "pct_vs_low": 0.0,
    "fetched_at": "2026-03-22T11:35:56.443129+00:00"
  },
  {
    "player_id": "11051",
    "player_name": "Gabriel Bortoleto",
    "type": "Driver",
    "race_number": 1,
    "race_name": "Australian Grand Prix",
    "race_flag": "🇦🇺",
    "race_date": "2026-03-08",
    "next_race_number": 2,
    "next_race_name": "Chinese Grand Prix",
    "price_this_race": 6.4,
    "price_prev_race": 6.4,
    "price_next_race": 7.0,
    "price_change": 0.6,
    "price_change_pct": 9.37,
    "gameday_points": 13,
    "total_points": 13,
    "season_high": 7.0,
    "season_low": 6.4,
    "pct_vs_high": -8.57,
    "pct_vs_low": 0.0,
    "fetched_at": "2026-03-22T11:35:57.319620+00:00"
  },
  {
    "player_id": "124",
    "player_name": "George Russell",
    "type": "Driver",
    "race_number": 1,
    "race_name": "Australian Grand Prix",
    "race_flag": "🇦🇺",
    "race_date": "2026-03-08",
    "next_race_number": 2,
    "next_race_name": "Chinese Grand Prix",
    "price_this_race": 27.4,
    "price_prev_race": 27.4,
    "price_next_race": 27.7,
    "price_change": 0.3,
    "price_change_pct": 1.09,
    "gameday_points": 39,
    "total_points": 39,
    "season_high": 28.0,
    "season_low": 27.4,
    "pct_vs_high": -2.14,
    "pct_vs_low": 0.0,
    "fetched_at": "2026-03-22T11:35:57.975032+00:00"
  },
  {
    "player_id": "11032",
    "player_name": "Isack Hadjar",
    "type": "Driver",
    "race_number": 1,
    "race_name": "Australian Grand Prix",
    "race_flag": "🇦🇺",
    "race_date": "2026-03-08",
    "next_race_number": 2,
    "next_race_name": "Chinese Grand Prix",
    "price_this_race": 15.1,
    "price_prev_race": 15.1,
    "price_next_race": 14.5,
    "price_change": -0.6,
    "price_change_pct": -3.97,
    "gameday_points": -8,
    "total_points": -8,
    "season_high": 15.1,
    "season_low": 13.9,
    "pct_vs_high": 0.0,
    "pct_vs_low": 8.63,
    "fetched_at": "2026-03-22T11:35:58.899303+00:00"
  },
  {
    "player_id": "11161",
    "player_name": "Kimi Antonelli",
    "type": "Driver",
    "race_number": 1,
    "race_name": "Australian Grand Prix",
    "race_flag": "🇦🇺",
    "race_date": "2026-03-08",
    "next_race_number": 2,
    "next_race_name": "Chinese Grand Prix",
    "price_this_race": 23.2,
    "price_prev_race": 23.2,
    "price_next_race": 23.5,
    "price_change": 0.3,
    "price_change_pct": 1.29,
    "gameday_points": 32,
    "total_points": 32,
    "season_high": 23.8,
    "season_low": 23.2,
    "pct_vs_high": -2.52,
    "pct_vs_low": 0.0,
    "fetched_at": "2026-03-22T11:35:59.787028+00:00"
  },
  {
    "player_id": "129",
    "player_name": "Lance Stroll",
    "type": "Driver",
    "race_number": 1,
    "race_name": "Australian Grand Prix",
    "race_flag": "🇦🇺",
    "race_date": "2026-03-08",
    "next_race_number": 2,
    "next_race_name": "Chinese Grand Prix",
    "price_this_race": 8.0,
    "price_prev_race": 8.0,
    "price_next_race": 7.4,
    "price_change": -0.6,
    "price_change_pct": -7.5,
    "gameday_points": -23,
    "total_points": -23,
    "season_high": 8.0,
    "season_low": 6.8,
    "pct_vs_high": 0.0,
    "pct_vs_low": 17.65,
    "fetched_at": "2026-03-22T11:36:00.752629+00:00"
  },
  {
    "player_id": "117",
    "player_name": "Lando Norris",
    "type": "Driver",
    "race_number": 1,
    "race_name": "Australian Grand Prix",
    "race_flag": "🇦🇺",
    "race_date": "2026-03-08",
    "next_race_number": 2,
    "next_race_name": "Chinese Grand Prix",
    "price_this_race": 27.2,
    "price_prev_race": 27.2,
    "price_next_race": 27.1,
    "price_change": -0.1,
    "price_change_pct": -0.37,
    "gameday_points": 21,
    "total_points": 21,
    "season_high": 27.2,
    "season_low": 26.8,
    "pct_vs_high": 0.0,
    "pct_vs_low": 1.49,
    "fetched_at": "2026-03-22T11:36:01.619837+00:00"
  },
  {
    "player_id": "110",
    "player_name": "Lewis Hamilton",
    "type": "Driver",
    "race_number": 1,
    "race_name": "Australian Grand Prix",
    "race_flag": "🇦🇺",
    "race_date": "2026-03-08",
    "next_race_number": 2,
    "next_race_name": "Chinese Grand Prix",
    "price_this_race": 22.5,
    "price_prev_race": 22.5,
    "price_next_race": 22.6,
    "price_change": 0.1,
    "price_change_pct": 0.44,
    "gameday_points": 25,
    "total_points": 25,
    "season_high": 22.9,
    "season_low": 22.5,
    "pct_vs_high": -1.75,
    "pct_vs_low": 0.0,
    "fetched_at": "2026-03-22T11:36:02.587471+00:00"
  },
  {
    "player_id": "114",
    "player_name": "Liam Lawson",
    "type": "Driver",
    "race_number": 1,
    "race_name": "Australian Grand Prix",
    "race_flag": "🇦🇺",
    "race_date": "2026-03-08",
    "next_race_number": 2,
    "next_race_name": "Chinese Grand Prix",
    "price_this_race": 6.5,
    "price_prev_race": 6.5,
    "price_next_race": 6.3,
    "price_change": -0.2,
    "price_change_pct": -3.08,
    "gameday_points": 5,
    "total_points": 5,
    "season_high": 6.9,
    "season_low": 6.3,
    "pct_vs_high": -5.8,
    "pct_vs_low": 3.17,
    "fetched_at": "2026-03-22T11:36:03.509816+00:00"
  },
  {
    "player_id": "131",
    "player_name": "Max Verstappen",
    "type": "Driver",
    "race_number": 1,
    "race_name": "Australian Grand Prix",
    "race_flag": "🇦🇺",
    "race_date": "2026-03-08",
    "next_race_number": 2,
    "next_race_name": "Chinese Grand Prix",
    "price_this_race": 27.7,
    "price_prev_race": 27.7,
    "price_next_race": 28.0,
    "price_change": 0.3,
    "price_change_pct": 1.08,
    "gameday_points": 50,
    "total_points": 50,
    "season_high": 28.1,
    "season_low": 27.7,
    "pct_vs_high": -1.42,
    "pct_vs_low": 0.0,
    "fetched_at": "2026-03-22T11:36:04.120459+00:00"
  },
  {
    "player_id": "111",
    "player_name": "Nico Hulkenberg",
    "type": "Driver",
    "race_number": 1,
    "race_name": "Australian Grand Prix",
    "race_flag": "🇦🇺",
    "race_date": "2026-03-08",
    "next_race_number": 2,
    "next_race_name": "Chinese Grand Prix",
    "price_this_race": 6.8,
    "price_prev_race": 6.8,
    "price_next_race": 6.2,
    "price_change": -0.6,
    "price_change_pct": -8.82,
    "gameday_points": -20,
    "total_points": -20,
    "season_high": 6.8,
    "season_low": 5.6,
    "pct_vs_high": 0.0,
    "pct_vs_low": 21.43,
    "fetched_at": "2026-03-22T11:36:04.994388+00:00"
  },
  {
    "player_id": "11031",
    "player_name": "Oliver Bearman",
    "type": "Driver",
    "race_number": 1,
    "race_name": "Australian Grand Prix",
    "race_flag": "🇦🇺",
    "race_date": "2026-03-08",
    "next_race_number": 2,
    "next_race_name": "Chinese Grand Prix",
    "price_this_race": 7.4,
    "price_prev_race": 7.4,
    "price_next_race": 8.0,
    "price_change": 0.6,
    "price_change_pct": 8.11,
    "gameday_points": 20,
    "total_points": 20,
    "season_high": 8.6,
    "season_low": 7.4,
    "pct_vs_high": -13.95,
    "pct_vs_low": 0.0,
    "fetched_at": "2026-03-22T11:36:05.968241+00:00"
  },
  {
    "player_id": "1982",
    "player_name": "Oscar Piastri",
    "type": "Driver",
    "race_number": 1,
    "race_name": "Australian Grand Prix",
    "race_flag": "🇦🇺",
    "race_date": "2026-03-08",
    "next_race_number": 2,
    "next_race_name": "Chinese Grand Prix",
    "price_this_race": 25.5,
    "price_prev_race": 25.5,
    "price_next_race": 25.2,
    "price_change": -0.3,
    "price_change_pct": -1.18,
    "gameday_points": -14,
    "total_points": -14,
    "season_high": 25.5,
    "season_low": 24.9,
    "pct_vs_high": 0.0,
    "pct_vs_low": 2.41,
    "fetched_at": "2026-03-22T11:36:06.888662+00:00"
  },
  {
    "player_id": "18",
    "player_name": "Pierre Gasly",
    "type": "Driver",
    "race_number": 1,
    "race_name": "Australian Grand Prix",
    "race_flag": "🇦🇺",
    "race_date": "2026-03-08",
    "next_race_number": 2,
    "next_race_name": "Chinese Grand Prix",
    "price_this_race": 12.0,
    "price_prev_race": 12.0,
    "price_next_race": 12.2,
    "price_change": 0.2,
    "price_change_pct": 1.67,
    "gameday_points": 11,
    "total_points": 11,
    "season_high": 12.8,
    "season_low": 12.0,
    "pct_vs_high": -6.25,
    "pct_vs_low": 0.0,
    "fetched_at": "2026-03-22T11:36:07.757654+00:00"
  },
  {
    "player_id": "121",
    "player_name": "Sergio Perez",
    "type": "Driver",
    "race_number": 1,
    "race_name": "Australian Grand Prix",
    "race_flag": "🇦🇺",
    "race_date": "2026-03-08",
    "next_race_number": 2,
    "next_race_name": "Chinese Grand Prix",
    "price_this_race": 6.0,
    "price_prev_race": 6.0,
    "price_next_race": 5.8,
    "price_change": -0.2,
    "price_change_pct": -3.33,
    "gameday_points": 4,
    "total_points": 4,
    "season_high": 6.4,
    "season_low": 5.8,
    "pct_vs_high": -6.25,
    "pct_vs_low": 3.45,
    "fetched_at": "2026-03-22T11:36:08.416753+00:00"
  },
  {
    "player_id": "13",
    "player_name": "Valtteri Bottas",
    "type": "Driver",
    "race_number": 1,
    "race_name": "Australian Grand Prix",
    "race_flag": "🇦🇺",
    "race_date": "2026-03-08",
    "next_race_number": 2,
    "next_race_name": "Chinese Grand Prix",
    "price_this_race": 5.9,
    "price_prev_race": 5.9,
    "price_next_race": 5.3,
    "price_change": -0.6,
    "price_change_pct": -10.17,
    "gameday_points": -16,
    "total_points": -16,
    "season_high": 5.9,
    "season_low": 4.7,
    "pct_vs_high": 0.0,
    "pct_vs_low": 25.53,
    "fetched_at": "2026-03-22T11:36:09.343621+00:00"
  },
  {
    "player_id": "23",
    "player_name": "Alpine",
    "type": "Constructor",
    "race_number": 2,
    "race_name": "Chinese Grand Prix",
    "race_flag": "🇨🇳",
    "race_date": "2026-03-15",
    "next_race_number": 3,
    "next_race_name": "Japanese Grand Prix",
    "price_this_race": 13.1,
    "price_prev_race": 12.5,
    "price_next_race": 13.7,
    "price_change": 0.6,
    "price_change_pct": 4.58,
    "gameday_points": 45,
    "total_points": 67,
    "season_high": 13.7,
    "season_low": 12.5,
    "pct_vs_high": -4.38,
    "pct_vs_low": 4.8,
    "fetched_at": "2026-03-29T07:56:48.166060+00:00"
  },
  {
    "player_id": "24",
    "player_name": "Aston Martin",
    "type": "Constructor",
    "race_number": 2,
    "race_name": "Chinese Grand Prix",
    "race_flag": "🇨🇳",
    "race_date": "2026-03-15",
    "next_race_number": 3,
    "next_race_name": "Japanese Grand Prix",
    "price_this_race": 9.7,
    "price_prev_race": 10.3,
    "price_next_race": 9.1,
    "price_change": -0.6,
    "price_change_pct": -6.19,
    "gameday_points": -20,
    "total_points": -58,
    "season_high": 10.3,
    "season_low": 9.1,
    "pct_vs_high": -5.83,
    "pct_vs_low": 6.59,
    "fetched_at": "2026-03-29T07:56:49.254128+00:00"
  },
  {
    "player_id": "2640",
    "player_name": "Audi",
    "type": "Constructor",
    "race_number": 2,
    "race_name": "Chinese Grand Prix",
    "race_flag": "🇨🇳",
    "race_date": "2026-03-15",
    "next_race_number": 3,
    "next_race_name": "Japanese Grand Prix",
    "price_this_race": 6.0,
    "price_prev_race": 6.6,
    "price_next_race": 5.4,
    "price_change": -0.6,
    "price_change_pct": -10.0,
    "gameday_points": -4,
    "total_points": -4,
    "season_high": 6.6,
    "season_low": 5.4,
    "pct_vs_high": -9.09,
    "pct_vs_low": 11.11,
    "fetched_at": "2026-03-29T07:56:49.872695+00:00"
  },
  {
    "player_id": "2641",
    "player_name": "Cadillac",
    "type": "Constructor",
    "race_number": 2,
    "race_name": "Chinese Grand Prix",
    "race_flag": "🇨🇳",
    "race_date": "2026-03-15",
    "next_race_number": 3,
    "next_race_name": "Japanese Grand Prix",
    "price_this_race": 5.4,
    "price_prev_race": 6.0,
    "price_next_race": 5.2,
    "price_change": -0.2,
    "price_change_pct": -3.7,
    "gameday_points": 22,
    "total_points": 9,
    "season_high": 6.0,
    "season_low": 5.2,
    "pct_vs_high": -10.0,
    "pct_vs_low": 3.85,
    "fetched_at": "2026-03-29T07:56:50.792891+00:00"
  },
  {
    "player_id": "25",
    "player_name": "Ferrari",
    "type": "Constructor",
    "race_number": 2,
    "race_name": "Chinese Grand Prix",
    "race_flag": "🇨🇳",
    "race_date": "2026-03-15",
    "next_race_number": 3,
    "next_race_name": "Japanese Grand Prix",
    "price_this_race": 23.6,
    "price_prev_race": 23.3,
    "price_next_race": 23.9,
    "price_change": 0.3,
    "price_change_pct": 1.27,
    "gameday_points": 119,
    "total_points": 188,
    "season_high": 23.9,
    "season_low": 23.3,
    "pct_vs_high": -1.26,
    "pct_vs_low": 1.29,
    "fetched_at": "2026-03-29T07:56:51.404113+00:00"
  },
  {
    "player_id": "26",
    "player_name": "Haas F1 Team",
    "type": "Constructor",
    "race_number": 2,
    "race_name": "Chinese Grand Prix",
    "race_flag": "🇨🇳",
    "race_date": "2026-03-15",
    "next_race_number": 3,
    "next_race_name": "Japanese Grand Prix",
    "price_this_race": 8.0,
    "price_prev_race": 7.4,
    "price_next_race": 8.6,
    "price_change": 0.6,
    "price_change_pct": 7.5,
    "gameday_points": 65,
    "total_points": 99,
    "season_high": 8.6,
    "season_low": 7.4,
    "pct_vs_high": -6.98,
    "pct_vs_low": 8.11,
    "fetched_at": "2026-03-29T07:56:52.320383+00:00"
  },
  {
    "player_id": "27",
    "player_name": "McLaren",
    "type": "Constructor",
    "race_number": 2,
    "race_name": "Chinese Grand Prix",
    "race_flag": "🇨🇳",
    "race_date": "2026-03-15",
    "next_race_number": 3,
    "next_race_name": "Japanese Grand Prix",
    "price_this_race": 28.8,
    "price_prev_race": 28.9,
    "price_next_race": 28.5,
    "price_change": -0.3,
    "price_change_pct": -1.04,
    "gameday_points": -7,
    "total_points": 12,
    "season_high": 28.9,
    "season_low": 28.5,
    "pct_vs_high": -0.35,
    "pct_vs_low": 1.05,
    "fetched_at": "2026-03-29T07:56:53.165088+00:00"
  },
  {
    "player_id": "28",
    "player_name": "Mercedes",
    "type": "Constructor",
    "race_number": 2,
    "race_name": "Chinese Grand Prix",
    "race_flag": "🇨🇳",
    "race_date": "2026-03-15",
    "next_race_number": 3,
    "next_race_name": "Japanese Grand Prix",
    "price_this_race": 29.6,
    "price_prev_race": 29.3,
    "price_next_race": 29.9,
    "price_change": 0.3,
    "price_change_pct": 1.01,
    "gameday_points": 115,
    "total_points": 211,
    "season_high": 29.9,
    "season_low": 29.3,
    "pct_vs_high": -1.0,
    "pct_vs_low": 1.02,
    "fetched_at": "2026-03-29T07:56:54.069115+00:00"
  },
  {
    "player_id": "2636",
    "player_name": "Racing Bulls",
    "type": "Constructor",
    "race_number": 2,
    "race_name": "Chinese Grand Prix",
    "race_flag": "🇨🇳",
    "race_date": "2026-03-15",
    "next_race_number": 3,
    "next_race_name": "Japanese Grand Prix",
    "price_this_race": 6.9,
    "price_prev_race": 6.3,
    "price_next_race": 7.5,
    "price_change": 0.6,
    "price_change_pct": 8.7,
    "gameday_points": 50,
    "total_points": 85,
    "season_high": 7.5,
    "season_low": 6.3,
    "pct_vs_high": -8.0,
    "pct_vs_low": 9.52,
    "fetched_at": "2026-03-29T07:56:54.993729+00:00"
  },
  {
    "player_id": "29",
    "player_name": "Red Bull Racing",
    "type": "Constructor",
    "race_number": 2,
    "race_name": "Chinese Grand Prix",
    "race_flag": "🇨🇳",
    "race_date": "2026-03-15",
    "next_race_number": 3,
    "next_race_name": "Japanese Grand Prix",
    "price_this_race": 28.5,
    "price_prev_race": 28.2,
    "price_next_race": 28.8,
    "price_change": 0.3,
    "price_change_pct": 1.05,
    "gameday_points": 45,
    "total_points": 87,
    "season_high": 28.8,
    "season_low": 28.2,
    "pct_vs_high": -1.04,
    "pct_vs_low": 1.06,
    "fetched_at": "2026-03-29T07:56:55.911652+00:00"
  },
  {
    "player_id": "210",
    "player_name": "Williams",
    "type": "Constructor",
    "race_number": 2,
    "race_name": "Chinese Grand Prix",
    "race_flag": "🇨🇳",
    "race_date": "2026-03-15",
    "next_race_number": 3,
    "next_race_name": "Japanese Grand Prix",
    "price_this_race": 12.6,
    "price_prev_race": 12.0,
    "price_next_race": 13.2,
    "price_change": 0.6,
    "price_change_pct": 4.76,
    "gameday_points": 22,
    "total_points": 42,
    "season_high": 13.2,
    "season_low": 12.0,
    "pct_vs_high": -4.55,
    "pct_vs_low": 5.0,
    "fetched_at": "2026-03-29T07:56:56.831811+00:00"
  },
  {
    "player_id": "11",
    "player_name": "Alexander Albon",
    "type": "Driver",
    "race_number": 2,
    "race_name": "Chinese Grand Prix",
    "race_flag": "🇨🇳",
    "race_date": "2026-03-15",
    "next_race_number": 3,
    "next_race_name": "Japanese Grand Prix",
    "price_this_race": 11.4,
    "price_prev_race": 11.6,
    "price_next_race": 10.8,
    "price_change": -0.6,
    "price_change_pct": -5.26,
    "gameday_points": -7,
    "total_points": 1,
    "season_high": 11.6,
    "season_low": 10.8,
    "pct_vs_high": -1.72,
    "pct_vs_low": 5.56,
    "fetched_at": "2026-03-29T07:56:23.247976+00:00"
  },
  {
    "player_id": "11149",
    "player_name": "Arvid Lindblad",
    "type": "Driver",
    "race_number": 2,
    "race_name": "Chinese Grand Prix",
    "race_flag": "🇨🇳",
    "race_date": "2026-03-15",
    "next_race_number": 3,
    "next_race_name": "Japanese Grand Prix",
    "price_this_race": 6.8,
    "price_prev_race": 6.2,
    "price_next_race": 7.4,
    "price_change": 0.6,
    "price_change_pct": 8.82,
    "gameday_points": 7,
    "total_points": 22,
    "season_high": 7.4,
    "season_low": 6.2,
    "pct_vs_high": -8.11,
    "pct_vs_low": 9.68,
    "fetched_at": "2026-03-29T07:56:24.686302+00:00"
  },
  {
    "player_id": "125",
    "player_name": "Carlos Sainz",
    "type": "Driver",
    "race_number": 2,
    "race_name": "Chinese Grand Prix",
    "race_flag": "🇨🇳",
    "race_date": "2026-03-15",
    "next_race_number": 3,
    "next_race_name": "Japanese Grand Prix",
    "price_this_race": 11.6,
    "price_prev_race": 11.8,
    "price_next_race": 12.2,
    "price_change": 0.6,
    "price_change_pct": 5.17,
    "gameday_points": 28,
    "total_points": 37,
    "season_high": 12.2,
    "season_low": 11.6,
    "pct_vs_high": -4.92,
    "pct_vs_low": 0.0,
    "fetched_at": "2026-03-29T07:56:26.111466+00:00"
  },
  {
    "player_id": "115",
    "player_name": "Charles Leclerc",
    "type": "Driver",
    "race_number": 2,
    "race_name": "Chinese Grand Prix",
    "race_flag": "🇨🇳",
    "race_date": "2026-03-15",
    "next_race_number": 3,
    "next_race_name": "Japanese Grand Prix",
    "price_this_race": 23.1,
    "price_prev_race": 22.8,
    "price_next_race": 23.4,
    "price_change": 0.3,
    "price_change_pct": 1.3,
    "gameday_points": 51,
    "total_points": 80,
    "season_high": 23.4,
    "season_low": 22.8,
    "pct_vs_high": -1.28,
    "pct_vs_low": 1.32,
    "fetched_at": "2026-03-29T07:56:27.723329+00:00"
  },
  {
    "player_id": "118",
    "player_name": "Esteban Ocon",
    "type": "Driver",
    "race_number": 2,
    "race_name": "Chinese Grand Prix",
    "race_flag": "🇨🇳",
    "race_date": "2026-03-15",
    "next_race_number": 3,
    "next_race_name": "Japanese Grand Prix",
    "price_this_race": 7.9,
    "price_prev_race": 7.3,
    "price_next_race": 8.5,
    "price_change": 0.6,
    "price_change_pct": 7.59,
    "gameday_points": 24,
    "total_points": 33,
    "season_high": 8.5,
    "season_low": 7.3,
    "pct_vs_high": -7.06,
    "pct_vs_low": 8.22,
    "fetched_at": "2026-03-29T07:56:29.290664+00:00"
  },
  {
    "player_id": "12",
    "player_name": "Fernando Alonso",
    "type": "Driver",
    "race_number": 2,
    "race_name": "Chinese Grand Prix",
    "race_flag": "🇨🇳",
    "race_date": "2026-03-15",
    "next_race_number": 3,
    "next_race_name": "Japanese Grand Prix",
    "price_this_race": 9.4,
    "price_prev_race": 10.0,
    "price_next_race": 8.8,
    "price_change": -0.6,
    "price_change_pct": -6.38,
    "gameday_points": -7,
    "total_points": -21,
    "season_high": 10.0,
    "season_low": 8.8,
    "pct_vs_high": -6.0,
    "pct_vs_low": 6.82,
    "fetched_at": "2026-03-29T07:56:30.910626+00:00"
  },
  {
    "player_id": "11059",
    "player_name": "Franco Colapinto",
    "type": "Driver",
    "race_number": 2,
    "race_name": "Chinese Grand Prix",
    "race_flag": "🇨🇳",
    "race_date": "2026-03-15",
    "next_race_number": 3,
    "next_race_name": "Japanese Grand Prix",
    "price_this_race": 6.4,
    "price_prev_race": 6.2,
    "price_next_race": 7.0,
    "price_change": 0.6,
    "price_change_pct": 9.37,
    "gameday_points": 18,
    "total_points": 24,
    "season_high": 7.0,
    "season_low": 6.2,
    "pct_vs_high": -8.57,
    "pct_vs_low": 3.23,
    "fetched_at": "2026-03-29T07:56:32.350562+00:00"
  },
  {
    "player_id": "11051",
    "player_name": "Gabriel Bortoleto",
    "type": "Driver",
    "race_number": 2,
    "race_name": "Chinese Grand Prix",
    "race_flag": "🇨🇳",
    "race_date": "2026-03-15",
    "next_race_number": 3,
    "next_race_name": "Japanese Grand Prix",
    "price_this_race": 7.0,
    "price_prev_race": 6.4,
    "price_next_race": 6.4,
    "price_change": -0.6,
    "price_change_pct": -8.57,
    "gameday_points": -14,
    "total_points": -1,
    "season_high": 7.0,
    "season_low": 6.4,
    "pct_vs_high": 0.0,
    "pct_vs_low": 9.37,
    "fetched_at": "2026-03-29T07:56:33.898598+00:00"
  },
  {
    "player_id": "124",
    "player_name": "George Russell",
    "type": "Driver",
    "race_number": 2,
    "race_name": "Chinese Grand Prix",
    "race_flag": "🇨🇳",
    "race_date": "2026-03-15",
    "next_race_number": 3,
    "next_race_name": "Japanese Grand Prix",
    "price_this_race": 27.7,
    "price_prev_race": 27.4,
    "price_next_race": 28.0,
    "price_change": 0.3,
    "price_change_pct": 1.08,
    "gameday_points": 45,
    "total_points": 84,
    "season_high": 28.0,
    "season_low": 27.4,
    "pct_vs_high": -1.07,
    "pct_vs_low": 1.09,
    "fetched_at": "2026-03-29T07:56:35.431007+00:00"
  },
  {
    "player_id": "11032",
    "player_name": "Isack Hadjar",
    "type": "Driver",
    "race_number": 2,
    "race_name": "Chinese Grand Prix",
    "race_flag": "🇨🇳",
    "race_date": "2026-03-15",
    "next_race_number": 3,
    "next_race_name": "Japanese Grand Prix",
    "price_this_race": 14.5,
    "price_prev_race": 15.1,
    "price_next_race": 13.9,
    "price_change": -0.6,
    "price_change_pct": -4.14,
    "gameday_points": 19,
    "total_points": 11,
    "season_high": 15.1,
    "season_low": 13.9,
    "pct_vs_high": -3.97,
    "pct_vs_low": 4.32,
    "fetched_at": "2026-03-29T07:56:36.458580+00:00"
  },
  {
    "player_id": "11161",
    "player_name": "Kimi Antonelli",
    "type": "Driver",
    "race_number": 2,
    "race_name": "Chinese Grand Prix",
    "race_flag": "🇨🇳",
    "race_date": "2026-03-15",
    "next_race_number": 3,
    "next_race_name": "Japanese Grand Prix",
    "price_this_race": 23.5,
    "price_prev_race": 23.2,
    "price_next_race": 23.8,
    "price_change": 0.3,
    "price_change_pct": 1.28,
    "gameday_points": 68,
    "total_points": 100,
    "season_high": 23.8,
    "season_low": 23.2,
    "pct_vs_high": -1.26,
    "pct_vs_low": 1.29,
    "fetched_at": "2026-03-29T07:56:37.312736+00:00"
  },
  {
    "player_id": "129",
    "player_name": "Lance Stroll",
    "type": "Driver",
    "race_number": 2,
    "race_name": "Chinese Grand Prix",
    "race_flag": "🇨🇳",
    "race_date": "2026-03-15",
    "next_race_number": 3,
    "next_race_name": "Japanese Grand Prix",
    "price_this_race": 7.4,
    "price_prev_race": 8.0,
    "price_next_race": 6.8,
    "price_change": -0.6,
    "price_change_pct": -8.11,
    "gameday_points": -14,
    "total_points": -37,
    "season_high": 8.0,
    "season_low": 6.8,
    "pct_vs_high": -7.5,
    "pct_vs_low": 8.82,
    "fetched_at": "2026-03-29T07:56:37.902673+00:00"
  },
  {
    "player_id": "117",
    "player_name": "Lando Norris",
    "type": "Driver",
    "race_number": 2,
    "race_name": "Chinese Grand Prix",
    "race_flag": "🇨🇳",
    "race_date": "2026-03-15",
    "next_race_number": 3,
    "next_race_name": "Japanese Grand Prix",
    "price_this_race": 27.1,
    "price_prev_race": 27.2,
    "price_next_race": 26.8,
    "price_change": -0.3,
    "price_change_pct": -1.11,
    "gameday_points": -10,
    "total_points": 11,
    "season_high": 27.2,
    "season_low": 26.8,
    "pct_vs_high": -0.37,
    "pct_vs_low": 1.12,
    "fetched_at": "2026-03-29T07:56:38.814089+00:00"
  },
  {
    "player_id": "110",
    "player_name": "Lewis Hamilton",
    "type": "Driver",
    "race_number": 2,
    "race_name": "Chinese Grand Prix",
    "race_flag": "🇨🇳",
    "race_date": "2026-03-15",
    "next_race_number": 3,
    "next_race_name": "Japanese Grand Prix",
    "price_this_race": 22.6,
    "price_prev_race": 22.5,
    "price_next_race": 22.9,
    "price_change": 0.3,
    "price_change_pct": 1.33,
    "gameday_points": 48,
    "total_points": 73,
    "season_high": 22.9,
    "season_low": 22.5,
    "pct_vs_high": -1.31,
    "pct_vs_low": 0.44,
    "fetched_at": "2026-03-29T07:56:39.705067+00:00"
  },
  {
    "player_id": "114",
    "player_name": "Liam Lawson",
    "type": "Driver",
    "race_number": 2,
    "race_name": "Chinese Grand Prix",
    "race_flag": "🇨🇳",
    "race_date": "2026-03-15",
    "next_race_number": 3,
    "next_race_name": "Japanese Grand Prix",
    "price_this_race": 6.3,
    "price_prev_race": 6.5,
    "price_next_race": 6.9,
    "price_change": 0.6,
    "price_change_pct": 9.52,
    "gameday_points": 35,
    "total_points": 40,
    "season_high": 6.9,
    "season_low": 6.3,
    "pct_vs_high": -8.7,
    "pct_vs_low": 0.0,
    "fetched_at": "2026-03-29T07:56:40.653660+00:00"
  },
  {
    "player_id": "131",
    "player_name": "Max Verstappen",
    "type": "Driver",
    "race_number": 2,
    "race_name": "Chinese Grand Prix",
    "race_flag": "🇨🇳",
    "race_date": "2026-03-15",
    "next_race_number": 3,
    "next_race_name": "Japanese Grand Prix",
    "price_this_race": 28.0,
    "price_prev_race": 27.7,
    "price_next_race": 28.1,
    "price_change": 0.1,
    "price_change_pct": 0.36,
    "gameday_points": 14,
    "total_points": 64,
    "season_high": 28.1,
    "season_low": 27.7,
    "pct_vs_high": -0.36,
    "pct_vs_low": 1.08,
    "fetched_at": "2026-03-29T07:56:41.512870+00:00"
  },
  {
    "player_id": "111",
    "player_name": "Nico Hulkenberg",
    "type": "Driver",
    "race_number": 2,
    "race_name": "Chinese Grand Prix",
    "race_flag": "🇨🇳",
    "race_date": "2026-03-15",
    "next_race_number": 3,
    "next_race_name": "Japanese Grand Prix",
    "price_this_race": 6.2,
    "price_prev_race": 6.8,
    "price_next_race": 5.6,
    "price_change": -0.6,
    "price_change_pct": -9.68,
    "gameday_points": 7,
    "total_points": -13,
    "season_high": 6.8,
    "season_low": 5.6,
    "pct_vs_high": -8.82,
    "pct_vs_low": 10.71,
    "fetched_at": "2026-03-29T07:56:42.367711+00:00"
  },
  {
    "player_id": "11031",
    "player_name": "Oliver Bearman",
    "type": "Driver",
    "race_number": 2,
    "race_name": "Chinese Grand Prix",
    "race_flag": "🇨🇳",
    "race_date": "2026-03-15",
    "next_race_number": 3,
    "next_race_name": "Japanese Grand Prix",
    "price_this_race": 8.0,
    "price_prev_race": 7.4,
    "price_next_race": 8.6,
    "price_change": 0.6,
    "price_change_pct": 7.5,
    "gameday_points": 34,
    "total_points": 54,
    "season_high": 8.6,
    "season_low": 7.4,
    "pct_vs_high": -6.98,
    "pct_vs_low": 8.11,
    "fetched_at": "2026-03-29T07:56:43.316791+00:00"
  },
  {
    "player_id": "1982",
    "player_name": "Oscar Piastri",
    "type": "Driver",
    "race_number": 2,
    "race_name": "Chinese Grand Prix",
    "race_flag": "🇨🇳",
    "race_date": "2026-03-15",
    "next_race_number": 3,
    "next_race_name": "Japanese Grand Prix",
    "price_this_race": 25.2,
    "price_prev_race": 25.5,
    "price_next_race": 24.9,
    "price_change": -0.3,
    "price_change_pct": -1.19,
    "gameday_points": -7,
    "total_points": -21,
    "season_high": 25.5,
    "season_low": 24.9,
    "pct_vs_high": -1.18,
    "pct_vs_low": 1.2,
    "fetched_at": "2026-03-29T07:56:44.341347+00:00"
  },
  {
    "player_id": "18",
    "player_name": "Pierre Gasly",
    "type": "Driver",
    "race_number": 2,
    "race_name": "Chinese Grand Prix",
    "race_flag": "🇨🇳",
    "race_date": "2026-03-15",
    "next_race_number": 3,
    "next_race_name": "Japanese Grand Prix",
    "price_this_race": 12.2,
    "price_prev_race": 12.0,
    "price_next_race": 12.8,
    "price_change": 0.6,
    "price_change_pct": 4.92,
    "gameday_points": 20,
    "total_points": 31,
    "season_high": 12.8,
    "season_low": 12.0,
    "pct_vs_high": -4.69,
    "pct_vs_low": 1.67,
    "fetched_at": "2026-03-29T07:56:45.370561+00:00"
  },
  {
    "player_id": "121",
    "player_name": "Sergio Perez",
    "type": "Driver",
    "race_number": 2,
    "race_name": "Chinese Grand Prix",
    "race_flag": "🇨🇳",
    "race_date": "2026-03-15",
    "next_race_number": 3,
    "next_race_name": "Japanese Grand Prix",
    "price_this_race": 5.8,
    "price_prev_race": 6.0,
    "price_next_race": 6.4,
    "price_change": 0.6,
    "price_change_pct": 10.34,
    "gameday_points": 20,
    "total_points": 24,
    "season_high": 6.4,
    "season_low": 5.8,
    "pct_vs_high": -9.38,
    "pct_vs_low": 0.0,
    "fetched_at": "2026-03-29T07:56:46.382452+00:00"
  },
  {
    "player_id": "13",
    "player_name": "Valtteri Bottas",
    "type": "Driver",
    "race_number": 2,
    "race_name": "Chinese Grand Prix",
    "race_flag": "🇨🇳",
    "race_date": "2026-03-15",
    "next_race_number": 3,
    "next_race_name": "Japanese Grand Prix",
    "price_this_race": 5.3,
    "price_prev_race": 5.9,
    "price_next_race": 4.7,
    "price_change": -0.6,
    "price_change_pct": -11.32,
    "gameday_points": 3,
    "total_points": -13,
    "season_high": 5.9,
    "season_low": 4.7,
    "pct_vs_high": -10.17,
    "pct_vs_low": 12.77,
    "fetched_at": "2026-03-29T07:56:47.302860+00:00"
  },
  {
    "player_id": "23",
    "player_name": "Alpine",
    "type": "Constructor",
    "race_number": 3,
    "race_name": "Japanese Grand Prix",
    "race_flag": "🇯🇵",
    "race_date": "2026-03-29",
    "next_race_number": 4,
    "next_race_name": "Miami Grand Prix",
    "price_this_race": 13.7,
    "price_prev_race": 13.1,
    "price_next_race": 14.3,
    "price_change": 0.6,
    "price_change_pct": 4.38,
    "gameday_points": 25,
    "total_points": 92,
    "season_high": 13.7,
    "season_low": 12.5,
    "pct_vs_high": 0.0,
    "pct_vs_low": 9.6,
    "fetched_at": "2026-03-29T14:45:19.191734+00:00"
  },
  {
    "player_id": "24",
    "player_name": "Aston Martin",
    "type": "Constructor",
    "race_number": 3,
    "race_name": "Japanese Grand Prix",
    "race_flag": "🇯🇵",
    "race_date": "2026-03-29",
    "next_race_number": 4,
    "next_race_name": "Miami Grand Prix",
    "price_this_race": 9.1,
    "price_prev_race": 9.7,
    "price_next_race": 8.5,
    "price_change": -0.6,
    "price_change_pct": -6.59,
    "gameday_points": -12,
    "total_points": -70,
    "season_high": 10.3,
    "season_low": 9.1,
    "pct_vs_high": -11.65,
    "pct_vs_low": 0.0,
    "fetched_at": "2026-03-29T14:45:20.203197+00:00"
  },
  {
    "player_id": "2640",
    "player_name": "Audi",
    "type": "Constructor",
    "race_number": 3,
    "race_name": "Japanese Grand Prix",
    "race_flag": "🇯🇵",
    "race_date": "2026-03-29",
    "next_race_number": 4,
    "next_race_name": "Miami Grand Prix",
    "price_this_race": 5.4,
    "price_prev_race": 6.0,
    "price_next_race": 5.6,
    "price_change": 0.2,
    "price_change_pct": 3.7,
    "gameday_points": 23,
    "total_points": 19,
    "season_high": 6.6,
    "season_low": 5.4,
    "pct_vs_high": -18.18,
    "pct_vs_low": 0.0,
    "fetched_at": "2026-03-29T14:45:21.183267+00:00"
  },
  {
    "player_id": "2641",
    "player_name": "Cadillac",
    "type": "Constructor",
    "race_number": 3,
    "race_name": "Japanese Grand Prix",
    "race_flag": "🇯🇵",
    "race_date": "2026-03-29",
    "next_race_number": 4,
    "next_race_name": "Miami Grand Prix",
    "price_this_race": 5.2,
    "price_prev_race": 5.4,
    "price_next_race": 5.4,
    "price_change": 0.2,
    "price_change_pct": 3.85,
    "gameday_points": 5,
    "total_points": 14,
    "season_high": 6.0,
    "season_low": 5.2,
    "pct_vs_high": -13.33,
    "pct_vs_low": 0.0,
    "fetched_at": "2026-03-29T14:45:22.156289+00:00"
  },
  {
    "player_id": "25",
    "player_name": "Ferrari",
    "type": "Constructor",
    "race_number": 3,
    "race_name": "Japanese Grand Prix",
    "race_flag": "🇯🇵",
    "race_date": "2026-03-29",
    "next_race_number": 4,
    "next_race_name": "Miami Grand Prix",
    "price_this_race": 23.9,
    "price_prev_race": 23.6,
    "price_next_race": 24.2,
    "price_change": 0.3,
    "price_change_pct": 1.26,
    "gameday_points": 75,
    "total_points": 263,
    "season_high": 23.9,
    "season_low": 23.3,
    "pct_vs_high": 0.0,
    "pct_vs_low": 2.58,
    "fetched_at": "2026-03-29T14:45:23.154482+00:00"
  },
  {
    "player_id": "26",
    "player_name": "Haas F1 Team",
    "type": "Constructor",
    "race_number": 3,
    "race_name": "Japanese Grand Prix",
    "race_flag": "🇯🇵",
    "race_date": "2026-03-29",
    "next_race_number": 4,
    "next_race_name": "Miami Grand Prix",
    "price_this_race": 8.6,
    "price_prev_race": 8.0,
    "price_next_race": 9.2,
    "price_change": 0.6,
    "price_change_pct": 6.98,
    "gameday_points": -4,
    "total_points": 95,
    "season_high": 8.6,
    "season_low": 7.4,
    "pct_vs_high": 0.0,
    "pct_vs_low": 16.22,
    "fetched_at": "2026-03-29T14:45:24.134034+00:00"
  },
  {
    "player_id": "27",
    "player_name": "McLaren",
    "type": "Constructor",
    "race_number": 3,
    "race_name": "Japanese Grand Prix",
    "race_flag": "🇯🇵",
    "race_date": "2026-03-29",
    "next_race_number": 4,
    "next_race_name": "Miami Grand Prix",
    "price_this_race": 28.5,
    "price_prev_race": 28.8,
    "price_next_race": 28.6,
    "price_change": 0.1,
    "price_change_pct": 0.35,
    "gameday_points": 72,
    "total_points": 84,
    "season_high": 28.9,
    "season_low": 28.5,
    "pct_vs_high": -1.38,
    "pct_vs_low": 0.0,
    "fetched_at": "2026-03-29T14:45:25.124954+00:00"
  },
  {
    "player_id": "28",
    "player_name": "Mercedes",
    "type": "Constructor",
    "race_number": 3,
    "race_name": "Japanese Grand Prix",
    "race_flag": "🇯🇵",
    "race_date": "2026-03-29",
    "next_race_number": 4,
    "next_race_name": "Miami Grand Prix",
    "price_this_race": 29.9,
    "price_prev_race": 29.6,
    "price_next_race": 30.2,
    "price_change": 0.3,
    "price_change_pct": 1.0,
    "gameday_points": 92,
    "total_points": 303,
    "season_high": 29.9,
    "season_low": 29.3,
    "pct_vs_high": 0.0,
    "pct_vs_low": 2.05,
    "fetched_at": "2026-03-29T14:45:25.791280+00:00"
  },
  {
    "player_id": "2636",
    "player_name": "Racing Bulls",
    "type": "Constructor",
    "race_number": 3,
    "race_name": "Japanese Grand Prix",
    "race_flag": "🇯🇵",
    "race_date": "2026-03-29",
    "next_race_number": 4,
    "next_race_name": "Miami Grand Prix",
    "price_this_race": 7.5,
    "price_prev_race": 6.9,
    "price_next_race": 8.1,
    "price_change": 0.6,
    "price_change_pct": 8.0,
    "gameday_points": 18,
    "total_points": 103,
    "season_high": 7.5,
    "season_low": 6.3,
    "pct_vs_high": 0.0,
    "pct_vs_low": 19.05,
    "fetched_at": "2026-03-29T14:45:26.815569+00:00"
  },
  {
    "player_id": "29",
    "player_name": "Red Bull Racing",
    "type": "Constructor",
    "race_number": 3,
    "race_name": "Japanese Grand Prix",
    "race_flag": "🇯🇵",
    "race_date": "2026-03-29",
    "next_race_number": 4,
    "next_race_name": "Miami Grand Prix",
    "price_this_race": 28.8,
    "price_prev_race": 28.5,
    "price_next_race": 29.1,
    "price_change": 0.3,
    "price_change_pct": 1.04,
    "gameday_points": 25,
    "total_points": 112,
    "season_high": 28.8,
    "season_low": 28.2,
    "pct_vs_high": 0.0,
    "pct_vs_low": 2.13,
    "fetched_at": "2026-03-29T14:45:27.837859+00:00"
  },
  {
    "player_id": "210",
    "player_name": "Williams",
    "type": "Constructor",
    "race_number": 3,
    "race_name": "Japanese Grand Prix",
    "race_flag": "🇯🇵",
    "race_date": "2026-03-29",
    "next_race_number": 4,
    "next_race_name": "Miami Grand Prix",
    "price_this_race": 13.2,
    "price_prev_race": 12.6,
    "price_next_race": 13.8,
    "price_change": 0.6,
    "price_change_pct": 4.55,
    "gameday_points": 9,
    "total_points": 51,
    "season_high": 13.2,
    "season_low": 12.0,
    "pct_vs_high": 0.0,
    "pct_vs_low": 10.0,
    "fetched_at": "2026-03-29T14:45:28.855844+00:00"
  },
  {
    "player_id": "11",
    "player_name": "Alexander Albon",
    "type": "Driver",
    "race_number": 3,
    "race_name": "Japanese Grand Prix",
    "race_flag": "🇯🇵",
    "race_date": "2026-03-29",
    "next_race_number": 4,
    "next_race_name": "Miami Grand Prix",
    "price_this_race": 10.8,
    "price_prev_race": 11.4,
    "price_next_race": 10.2,
    "price_change": -0.6,
    "price_change_pct": -5.56,
    "gameday_points": -1,
    "total_points": 0,
    "season_high": 11.6,
    "season_low": 10.8,
    "pct_vs_high": -6.9,
    "pct_vs_low": 0.0,
    "fetched_at": "2026-03-29T14:44:51.752757+00:00"
  },
  {
    "player_id": "11149",
    "player_name": "Arvid Lindblad",
    "type": "Driver",
    "race_number": 3,
    "race_name": "Japanese Grand Prix",
    "race_flag": "🇯🇵",
    "race_date": "2026-03-29",
    "next_race_number": 4,
    "next_race_name": "Miami Grand Prix",
    "price_this_race": 7.4,
    "price_prev_race": 6.8,
    "price_next_race": 7.6,
    "price_change": 0.2,
    "price_change_pct": 2.7,
    "gameday_points": 1,
    "total_points": 23,
    "season_high": 7.4,
    "season_low": 6.2,
    "pct_vs_high": 0.0,
    "pct_vs_low": 19.35,
    "fetched_at": "2026-03-29T14:44:53.310697+00:00"
  },
  {
    "player_id": "125",
    "player_name": "Carlos Sainz",
    "type": "Driver",
    "race_number": 3,
    "race_name": "Japanese Grand Prix",
    "race_flag": "🇯🇵",
    "race_date": "2026-03-29",
    "next_race_number": 4,
    "next_race_name": "Miami Grand Prix",
    "price_this_race": 12.2,
    "price_prev_race": 11.6,
    "price_next_race": 12.4,
    "price_change": 0.2,
    "price_change_pct": 1.64,
    "gameday_points": 4,
    "total_points": 41,
    "season_high": 12.2,
    "season_low": 11.6,
    "pct_vs_high": 0.0,
    "pct_vs_low": 5.17,
    "fetched_at": "2026-03-29T14:44:54.798775+00:00"
  },
  {
    "player_id": "115",
    "player_name": "Charles Leclerc",
    "type": "Driver",
    "race_number": 3,
    "race_name": "Japanese Grand Prix",
    "race_flag": "🇯🇵",
    "race_date": "2026-03-29",
    "next_race_number": 4,
    "next_race_name": "Miami Grand Prix",
    "price_this_race": 23.4,
    "price_prev_race": 23.1,
    "price_next_race": 23.7,
    "price_change": 0.3,
    "price_change_pct": 1.28,
    "gameday_points": 31,
    "total_points": 111,
    "season_high": 23.4,
    "season_low": 22.8,
    "pct_vs_high": 0.0,
    "pct_vs_low": 2.63,
    "fetched_at": "2026-03-29T14:44:56.298996+00:00"
  },
  {
    "player_id": "118",
    "player_name": "Esteban Ocon",
    "type": "Driver",
    "race_number": 3,
    "race_name": "Japanese Grand Prix",
    "race_flag": "🇯🇵",
    "race_date": "2026-03-29",
    "next_race_number": 4,
    "next_race_name": "Miami Grand Prix",
    "price_this_race": 8.5,
    "price_prev_race": 7.9,
    "price_next_race": 9.1,
    "price_change": 0.6,
    "price_change_pct": 7.06,
    "gameday_points": 9,
    "total_points": 42,
    "season_high": 8.5,
    "season_low": 7.3,
    "pct_vs_high": 0.0,
    "pct_vs_low": 16.44,
    "fetched_at": "2026-03-29T14:44:57.837433+00:00"
  },
  {
    "player_id": "12",
    "player_name": "Fernando Alonso",
    "type": "Driver",
    "race_number": 3,
    "race_name": "Japanese Grand Prix",
    "race_flag": "🇯🇵",
    "race_date": "2026-03-29",
    "next_race_number": 4,
    "next_race_name": "Miami Grand Prix",
    "price_this_race": 8.8,
    "price_prev_race": 9.4,
    "price_next_race": 8.2,
    "price_change": -0.6,
    "price_change_pct": -6.82,
    "gameday_points": 4,
    "total_points": -17,
    "season_high": 10.0,
    "season_low": 8.8,
    "pct_vs_high": -12.0,
    "pct_vs_low": 0.0,
    "fetched_at": "2026-03-29T14:44:59.368359+00:00"
  },
  {
    "player_id": "11059",
    "player_name": "Franco Colapinto",
    "type": "Driver",
    "race_number": 3,
    "race_name": "Japanese Grand Prix",
    "race_flag": "🇯🇵",
    "race_date": "2026-03-29",
    "next_race_number": 4,
    "next_race_name": "Miami Grand Prix",
    "price_this_race": 7.0,
    "price_prev_race": 6.4,
    "price_next_race": 7.6,
    "price_change": 0.6,
    "price_change_pct": 8.57,
    "gameday_points": 4,
    "total_points": 28,
    "season_high": 7.0,
    "season_low": 6.2,
    "pct_vs_high": 0.0,
    "pct_vs_low": 12.9,
    "fetched_at": "2026-03-29T14:45:00.702747+00:00"
  },
  {
    "player_id": "11051",
    "player_name": "Gabriel Bortoleto",
    "type": "Driver",
    "race_number": 3,
    "race_name": "Japanese Grand Prix",
    "race_flag": "🇯🇵",
    "race_date": "2026-03-29",
    "next_race_number": 4,
    "next_race_name": "Miami Grand Prix",
    "price_this_race": 6.4,
    "price_prev_race": 7.0,
    "price_next_race": 5.8,
    "price_change": -0.6,
    "price_change_pct": -9.37,
    "gameday_points": 3,
    "total_points": 2,
    "season_high": 7.0,
    "season_low": 6.4,
    "pct_vs_high": -8.57,
    "pct_vs_low": 0.0,
    "fetched_at": "2026-03-29T14:45:02.248583+00:00"
  },
  {
    "player_id": "124",
    "player_name": "George Russell",
    "type": "Driver",
    "race_number": 3,
    "race_name": "Japanese Grand Prix",
    "race_flag": "🇯🇵",
    "race_date": "2026-03-29",
    "next_race_number": 4,
    "next_race_name": "Miami Grand Prix",
    "price_this_race": 28.0,
    "price_prev_race": 27.7,
    "price_next_race": 28.3,
    "price_change": 0.3,
    "price_change_pct": 1.07,
    "gameday_points": 27,
    "total_points": 111,
    "season_high": 28.0,
    "season_low": 27.4,
    "pct_vs_high": 0.0,
    "pct_vs_low": 2.19,
    "fetched_at": "2026-03-29T14:45:03.877180+00:00"
  },
  {
    "player_id": "11032",
    "player_name": "Isack Hadjar",
    "type": "Driver",
    "race_number": 3,
    "race_name": "Japanese Grand Prix",
    "race_flag": "🇯🇵",
    "race_date": "2026-03-29",
    "next_race_number": 4,
    "next_race_name": "Miami Grand Prix",
    "price_this_race": 13.9,
    "price_prev_race": 14.5,
    "price_next_race": 13.3,
    "price_change": -0.6,
    "price_change_pct": -4.32,
    "gameday_points": 5,
    "total_points": 16,
    "season_high": 15.1,
    "season_low": 13.9,
    "pct_vs_high": -7.95,
    "pct_vs_low": 0.0,
    "fetched_at": "2026-03-29T14:45:05.207879+00:00"
  },
  {
    "player_id": "11161",
    "player_name": "Kimi Antonelli",
    "type": "Driver",
    "race_number": 3,
    "race_name": "Japanese Grand Prix",
    "race_flag": "🇯🇵",
    "race_date": "2026-03-29",
    "next_race_number": 4,
    "next_race_name": "Miami Grand Prix",
    "price_this_race": 23.8,
    "price_prev_race": 23.5,
    "price_next_race": 24.1,
    "price_change": 0.3,
    "price_change_pct": 1.26,
    "gameday_points": 50,
    "total_points": 150,
    "season_high": 23.8,
    "season_low": 23.2,
    "pct_vs_high": 0.0,
    "pct_vs_low": 2.59,
    "fetched_at": "2026-03-29T14:45:06.845398+00:00"
  },
  {
    "player_id": "129",
    "player_name": "Lance Stroll",
    "type": "Driver",
    "race_number": 3,
    "race_name": "Japanese Grand Prix",
    "race_flag": "🇯🇵",
    "race_date": "2026-03-29",
    "next_race_number": 4,
    "next_race_name": "Miami Grand Prix",
    "price_this_race": 6.8,
    "price_prev_race": 7.4,
    "price_next_race": 6.2,
    "price_change": -0.6,
    "price_change_pct": -8.82,
    "gameday_points": -17,
    "total_points": -54,
    "season_high": 8.0,
    "season_low": 6.8,
    "pct_vs_high": -15.0,
    "pct_vs_low": 0.0,
    "fetched_at": "2026-03-29T14:45:08.485687+00:00"
  },
  {
    "player_id": "117",
    "player_name": "Lando Norris",
    "type": "Driver",
    "race_number": 3,
    "race_name": "Japanese Grand Prix",
    "race_flag": "🇯🇵",
    "race_date": "2026-03-29",
    "next_race_number": 4,
    "next_race_name": "Miami Grand Prix",
    "price_this_race": 26.8,
    "price_prev_race": 27.1,
    "price_next_race": 26.5,
    "price_change": -0.3,
    "price_change_pct": -1.12,
    "gameday_points": 24,
    "total_points": 35,
    "season_high": 27.2,
    "season_low": 26.8,
    "pct_vs_high": -1.47,
    "pct_vs_low": 0.0,
    "fetched_at": "2026-03-29T14:45:09.814005+00:00"
  },
  {
    "player_id": "110",
    "player_name": "Lewis Hamilton",
    "type": "Driver",
    "race_number": 3,
    "race_name": "Japanese Grand Prix",
    "race_flag": "🇯🇵",
    "race_date": "2026-03-29",
    "next_race_number": 4,
    "next_race_name": "Miami Grand Prix",
    "price_this_race": 22.9,
    "price_prev_race": 22.6,
    "price_next_race": 23.2,
    "price_change": 0.3,
    "price_change_pct": 1.31,
    "gameday_points": 19,
    "total_points": 92,
    "season_high": 22.9,
    "season_low": 22.5,
    "pct_vs_high": 0.0,
    "pct_vs_low": 1.78,
    "fetched_at": "2026-03-29T14:45:11.150567+00:00"
  },
  {
    "player_id": "114",
    "player_name": "Liam Lawson",
    "type": "Driver",
    "race_number": 3,
    "race_name": "Japanese Grand Prix",
    "race_flag": "🇯🇵",
    "race_date": "2026-03-29",
    "next_race_number": 4,
    "next_race_name": "Miami Grand Prix",
    "price_this_race": 6.9,
    "price_prev_race": 6.3,
    "price_next_race": 7.5,
    "price_change": 0.6,
    "price_change_pct": 8.7,
    "gameday_points": 10,
    "total_points": 50,
    "season_high": 6.9,
    "season_low": 6.3,
    "pct_vs_high": 0.0,
    "pct_vs_low": 9.52,
    "fetched_at": "2026-03-29T14:45:12.011041+00:00"
  },
  {
    "player_id": "131",
    "player_name": "Max Verstappen",
    "type": "Driver",
    "race_number": 3,
    "race_name": "Japanese Grand Prix",
    "race_flag": "🇯🇵",
    "race_date": "2026-03-29",
    "next_race_number": 4,
    "next_race_name": "Miami Grand Prix",
    "price_this_race": 28.1,
    "price_prev_race": 28.0,
    "price_next_race": 28.2,
    "price_change": 0.1,
    "price_change_pct": 0.36,
    "gameday_points": 13,
    "total_points": 77,
    "season_high": 28.1,
    "season_low": 27.7,
    "pct_vs_high": 0.0,
    "pct_vs_low": 1.44,
    "fetched_at": "2026-03-29T14:45:13.019389+00:00"
  },
  {
    "player_id": "111",
    "player_name": "Nico Hulkenberg",
    "type": "Driver",
    "race_number": 3,
    "race_name": "Japanese Grand Prix",
    "race_flag": "🇯🇵",
    "race_date": "2026-03-29",
    "next_race_number": 4,
    "next_race_name": "Miami Grand Prix",
    "price_this_race": 5.6,
    "price_prev_race": 6.2,
    "price_next_race": 5.0,
    "price_change": -0.6,
    "price_change_pct": -10.71,
    "gameday_points": 10,
    "total_points": -3,
    "season_high": 6.8,
    "season_low": 5.6,
    "pct_vs_high": -17.65,
    "pct_vs_low": 0.0,
    "fetched_at": "2026-03-29T14:45:13.880156+00:00"
  },
  {
    "player_id": "11031",
    "player_name": "Oliver Bearman",
    "type": "Driver",
    "race_number": 3,
    "race_name": "Japanese Grand Prix",
    "race_flag": "🇯🇵",
    "race_date": "2026-03-29",
    "next_race_number": 4,
    "next_race_name": "Miami Grand Prix",
    "price_this_race": 8.6,
    "price_prev_race": 8.0,
    "price_next_race": 9.2,
    "price_change": 0.6,
    "price_change_pct": 6.98,
    "gameday_points": -14,
    "total_points": 40,
    "season_high": 8.6,
    "season_low": 7.4,
    "pct_vs_high": 0.0,
    "pct_vs_low": 16.22,
    "fetched_at": "2026-03-29T14:45:14.749354+00:00"
  },
  {
    "player_id": "1982",
    "player_name": "Oscar Piastri",
    "type": "Driver",
    "race_number": 3,
    "race_name": "Japanese Grand Prix",
    "race_flag": "🇯🇵",
    "race_date": "2026-03-29",
    "next_race_number": 4,
    "next_race_name": "Miami Grand Prix",
    "price_this_race": 24.9,
    "price_prev_race": 25.2,
    "price_next_race": 24.6,
    "price_change": -0.3,
    "price_change_pct": -1.2,
    "gameday_points": 43,
    "total_points": 22,
    "season_high": 25.5,
    "season_low": 24.9,
    "pct_vs_high": -2.35,
    "pct_vs_low": 0.0,
    "fetched_at": "2026-03-29T14:45:15.654579+00:00"
  },
  {
    "player_id": "18",
    "player_name": "Pierre Gasly",
    "type": "Driver",
    "race_number": 3,
    "race_name": "Japanese Grand Prix",
    "race_flag": "🇯🇵",
    "race_date": "2026-03-29",
    "next_race_number": 4,
    "next_race_name": "Miami Grand Prix",
    "price_this_race": 12.8,
    "price_prev_race": 12.2,
    "price_next_race": 13.0,
    "price_change": 0.2,
    "price_change_pct": 1.56,
    "gameday_points": 14,
    "total_points": 45,
    "season_high": 12.8,
    "season_low": 12.0,
    "pct_vs_high": 0.0,
    "pct_vs_low": 6.67,
    "fetched_at": "2026-03-29T14:45:16.266651+00:00"
  },
  {
    "player_id": "121",
    "player_name": "Sergio Perez",
    "type": "Driver",
    "race_number": 3,
    "race_name": "Japanese Grand Prix",
    "race_flag": "🇯🇵",
    "race_date": "2026-03-29",
    "next_race_number": 4,
    "next_race_name": "Miami Grand Prix",
    "price_this_race": 6.4,
    "price_prev_race": 5.8,
    "price_next_race": 7.0,
    "price_change": 0.6,
    "price_change_pct": 9.37,
    "gameday_points": 4,
    "total_points": 28,
    "season_high": 6.4,
    "season_low": 5.8,
    "pct_vs_high": 0.0,
    "pct_vs_low": 10.34,
    "fetched_at": "2026-03-29T14:45:17.291022+00:00"
  },
  {
    "player_id": "13",
    "player_name": "Valtteri Bottas",
    "type": "Driver",
    "race_number": 3,
    "race_name": "Japanese Grand Prix",
    "race_flag": "🇯🇵",
    "race_date": "2026-03-29",
    "next_race_number": 4,
    "next_race_name": "Miami Grand Prix",
    "price_this_race": 4.7,
    "price_prev_race": 5.3,
    "price_next_race": 4.5,
    "price_change": -0.2,
    "price_change_pct": -4.26,
    "gameday_points": 2,
    "total_points": -11,
    "season_high": 5.9,
    "season_low": 4.7,
    "pct_vs_high": -20.34,
    "pct_vs_low": 0.0,
    "fetched_at": "2026-03-29T14:45:18.214096+00:00"
  }
]